requests_google/__init__.py
requests_google/api.py
requests_google/googlenews.py
requests_google/utils.py
requests_google/cli/__init__.py
requests_google/cli/requests_googlenews.py
requests_google-0.0.7.dist-info/LICENSE
requests_google-0.0.7.dist-info/METADATA
requests_google-0.0.7.dist-info/WHEEL
requests_google-0.0.7.dist-info/entry_points.txt
requests_google-0.0.7.dist-info/top_level.txt
requests_google-0.0.7.dist-info/RECORD
