Metadata-Version: 2.1
Name: requests-google
Version: 0.0.7
Summary: A simple google related Parsing Package.
Home-page: https://github.com/yangxuhui/requests-google
Author: Xuhui Yang
Author-email: yangxuhui1992@163.com
License: UNKNOWN
Keywords: google parse crawler
Platform: UNKNOWN
Classifier: Development Status :: 3 - Alpha
Classifier: Intended Audience :: Developers
Classifier: Topic :: Utilities
Classifier: License :: OSI Approved :: MIT License
Classifier: Programming Language :: Python :: 2
Classifier: Programming Language :: Python :: 2.7
Classifier: Programming Language :: Python :: 3
Classifier: Programming Language :: Python :: 3.5
Classifier: Programming Language :: Python :: 3.6
Classifier: Programming Language :: Python :: 3.7
Requires-Python: >=2.7, !=3.0.*, !=3.1.*, !=3.2.*, !=3.3.*, !=3.4.*, <4
Requires-Dist: requests
Requires-Dist: feedparser
